design.plone.ioprenoto-1.2.10-py3.11-nspkg.pth
design/plone/ioprenoto/__init__.py
design/plone/ioprenoto/configure.zcml
design/plone/ioprenoto/interfaces.py
design/plone/ioprenoto/permissions.zcml
design/plone/ioprenoto/setuphandlers.py
design/plone/ioprenoto/testing.py
design/plone/ioprenoto/utilities.py
design/plone/ioprenoto/adapters/__init__.py
design/plone/ioprenoto/adapters/configure.zcml
design/plone/ioprenoto/adapters/stringinterp.py
design/plone/ioprenoto/behaviors/__init__.py
design/plone/ioprenoto/behaviors/additional_fields.py
design/plone/ioprenoto/behaviors/configure.zcml
design/plone/ioprenoto/behaviors/metadata.py
design/plone/ioprenoto/browser/__init__.py
design/plone/ioprenoto/browser/configure.zcml
design/plone/ioprenoto/browser/overrides/.gitkeep
design/plone/ioprenoto/browser/static/.gitkeep
design/plone/ioprenoto/events/__init__.py
design/plone/ioprenoto/events/configure.zcml
design/plone/ioprenoto/events/on_create.py
design/plone/ioprenoto/locales/README.rst
design/plone/ioprenoto/locales/__init__.py
design/plone/ioprenoto/locales/design.plone.ioprenoto.pot
design/plone/ioprenoto/locales/update.py
design/plone/ioprenoto/locales/update.sh
design/plone/ioprenoto/locales/en/LC_MESSAGES/design.plone.ioprenoto.po
design/plone/ioprenoto/locales/it/LC_MESSAGES/design.plone.ioprenoto.po
design/plone/ioprenoto/profiles/default/browserlayer.xml
design/plone/ioprenoto/profiles/default/catalog.xml
design/plone/ioprenoto/profiles/default/metadata.xml
design/plone/ioprenoto/profiles/default/registry/main.xml
design/plone/ioprenoto/profiles/default/types/Prenotazione.xml
design/plone/ioprenoto/profiles/default/types/PrenotazioniFolder.xml
design/plone/ioprenoto/profiles/uninstall/browserlayer.xml
design/plone/ioprenoto/restapi/__init__.py
design/plone/ioprenoto/restapi/configure.zcml
design/plone/ioprenoto/restapi/serializers/__init__.py
design/plone/ioprenoto/restapi/serializers/configure.zcml
design/plone/ioprenoto/restapi/serializers/vocabularies.py
design.plone.ioprenoto-1.2.10.dist-info/LICENSE.GPL
design.plone.ioprenoto-1.2.10.dist-info/LICENSE.rst
design.plone.ioprenoto-1.2.10.dist-info/METADATA
design.plone.ioprenoto-1.2.10.dist-info/WHEEL
design.plone.ioprenoto-1.2.10.dist-info/entry_points.txt
design.plone.ioprenoto-1.2.10.dist-info/namespace_packages.txt
design.plone.ioprenoto-1.2.10.dist-info/top_level.txt
design.plone.ioprenoto-1.2.10.dist-info/RECORD
