Metadata-Version: 2.2
Name: design.plone.ioprenoto
Version: 1.2.10
Summary: An add-on for Plone
Home-page: https://github.com/RedTurtle/design.plone.ioprenoto
Author: RedTurtle
Author-email: info@redturtle.it
License: GPL version 2
Project-URL: PyPI, https://pypi.org/project/design.plone.ioprenoto/
Project-URL: Source, https://github.com/RedTurtle/design.plone.ioprenoto
Project-URL: Tracker, https://github.com/RedTurtle/design.plone.ioprenoto/issues
Keywords: Python Plone CMS
Classifier: Environment :: Web Environment
Classifier: Framework :: Plone
Classifier: Framework :: Plone :: Addon
Classifier: Framework :: Plone :: 6.0
Classifier: Programming Language :: Python
Classifier: Programming Language :: Python :: 3.8
Classifier: Programming Language :: Python :: 3.9
Classifier: Programming Language :: Python :: 3.10
Classifier: Programming Language :: Python :: 3.11
Classifier: Operating System :: OS Independent
Classifier: License :: OSI Approved :: GNU General Public License v2 (GPLv2)
Classifier: Development Status :: 5 - Production/Stable
Requires-Python: >=3.7
License-File: LICENSE.GPL
License-File: LICENSE.rst
Requires-Dist: setuptools
Requires-Dist: z3c.jbot
Requires-Dist: plone.api>=1.8.4
Requires-Dist: plone.app.dexterity
Requires-Dist: redturtle.prenotazioni>=2.2.0.dev0
Requires-Dist: design.plone.policy
Requires-Dist: plone.restapi>=9.6.0
Provides-Extra: test
Requires-Dist: plone.app.testing; extra == "test"
Requires-Dist: plone.testing>=5.0.0; extra == "test"
Requires-Dist: plone.app.contenttypes; extra == "test"
Requires-Dist: plone.app.robotframework[debug]; extra == "test"
Requires-Dist: collective.MockMailHost; extra == "test"
Requires-Dist: redturtle.prenotazioni; extra == "test"
Requires-Dist: design.plone.policy; extra == "test"
Dynamic: author
Dynamic: author-email
Dynamic: classifier
Dynamic: description
Dynamic: home-page
Dynamic: keywords
Dynamic: license
Dynamic: project-url
Dynamic: provides-extra
Dynamic: requires-dist
Dynamic: requires-python
Dynamic: summary
